README
setup.py
pysmile/__init__.py
pysmile/constants.py
pysmile/decode.py
pysmile/encode.py
pysmile/util.py
pysmile.egg-info/PKG-INFO
pysmile.egg-info/SOURCES.txt
pysmile.egg-info/dependency_links.txt
pysmile.egg-info/pbr.json
pysmile.egg-info/top_level.txt
tests/__init__.py
tests/pysmile_tests.py