Metadata-Version: 1.1
Name: pysmile
Version: 0.2
Summary: Tools for working with the SMILE data format
Home-page: https://github.com/jhosmer/PySmile
Author: Jonathan Hosmer
Author-email: jon@pythonforios.com
License: Apache License, Version 2.0
Keywords: json smile
Platform: Linux
Classifier: Development Status :: 4 - Beta
Classifier: Environment :: Console
Classifier: Intended Audience :: Developers
Classifier: License :: OSI Approved :: Apache Software License
Classifier: Operating System :: Unix
Classifier: Programming Language :: Python :: 2.7
Classifier: Topic :: Internet :: WWW/HTTP
Classifier: Topic :: Internet :: WWW/HTTP :: HTTP Servers
Classifier: Topic :: Utilities
